[
  {
    "timestamp": "2025-09-29T07:31:11.148Z",
    "performance": 100,
    "fcp": 0.25905700000000004,
    "lcp": 0.595328,
    "tbt": 0,
    "cls": 0,
    "speedIndex": 0.31110576667160195,
    "tti": 0.595328
  },
  {
    "timestamp": "2025-09-29T07:38:37.319Z",
    "performance": 100,
    "fcp": 0.254238,
    "lcp": 0.593202,
    "tbt": 0,
    "cls": 0,
    "speedIndex": 0.38230594998601675,
    "tti": 0.593202
  },
  {
    "timestamp": "2025-09-29T07:40:01.552Z",
    "performance": 100,
    "fcp": 0.250151,
    "lcp": 0.5993910000000001,
    "tbt": 0,
    "cls": 0,
    "speedIndex": 0.3070012583028992,
    "tti": 0.5993910000000001
  },
  {
    "timestamp": "2025-09-29T07:41:35.236Z",
    "performance": 100,
    "fcp": 0.260553,
    "lcp": 0.5986630000000001,
    "tbt": 0,
    "cls": 0,
    "speedIndex": 0.32715527501425745,
    "tti": 0.5986630000000001
  },
  {
    "timestamp": "2025-09-30T08:28:47.235Z",
    "performance": 100,
    "fcp": 0.2574970000000001,
    "lcp": 0.5977510000000001,
    "tbt": 0,
    "cls": 0,
    "speedIndex": 0.355422791674618,
    "tti": 0.5977510000000003
  },
  {
    "timestamp": "2025-09-30T08:42:40.598Z",
    "performance": 100,
    "fcp": 0.258835,
    "lcp": 0.6067059999999999,
    "tbt": 0,
    "cls": 0,
    "speedIndex": 0.35125121668092407,
    "tti": 0.6067059999999999
  },
  {
    "timestamp": "2025-09-30T08:43:40.034Z",
    "performance": 100,
    "fcp": 0.25923099999999993,
    "lcp": 0.598403,
    "tbt": 0,
    "cls": 0,
    "speedIndex": 0.38237229166173137,
    "tti": 0.598403
  },
  {
    "timestamp": "2025-09-30T08:46:50.285Z",
    "performance": 100,
    "fcp": 0.257683,
    "lcp": 0.6085430000000001,
    "tbt": 0,
    "cls": 0,
    "speedIndex": 0.31977051664747397,
    "tti": 0.6085430000000002
  },
  {
    "timestamp": "2025-09-30T08:55:21.461Z",
    "performance": 100,
    "fcp": 0.260666,
    "lcp": 0.61984,
    "tbt": 0,
    "cls": 0,
    "speedIndex": 0.37348683332428534,
    "tti": 0.61984
  },
  {
    "timestamp": "2025-09-30T08:55:42.108Z",
    "performance": 100,
    "fcp": 0.255811,
    "lcp": 0.605056,
    "tbt": 0,
    "cls": 0,
    "speedIndex": 0.3456968666461031,
    "tti": 0.605056
  },
  {
    "timestamp": "2025-09-30T08:56:03.316Z",
    "performance": 100,
    "fcp": 0.25482099999999996,
    "lcp": 0.25482099999999996,
    "tbt": 0,
    "cls": 0,
    "speedIndex": 0.301570491691343,
    "tti": 0.25482099999999996
  },
  {
    "timestamp": "2025-09-30T09:35:47.946Z",
    "performance": 100,
    "fcp": 0.252654,
    "lcp": 0.6007709999999999,
    "tbt": 0,
    "cls": 0,
    "speedIndex": 0.31554129997669456,
    "tti": 0.6007709999999999
  },
  {
    "timestamp": "2025-09-30T09:38:01.230Z",
    "performance": 100,
    "fcp": 0.251488,
    "lcp": 0.5966279999999999,
    "tbt": 0,
    "cls": 0,
    "speedIndex": 0.39448706666036043,
    "tti": 0.5966279999999999
  },
  {
    "timestamp": "2025-09-30T09:41:39.862Z",
    "performance": 100,
    "fcp": 0.255458,
    "lcp": 0.5952799999999999,
    "tbt": 0,
    "cls": 0,
    "speedIndex": 0.327115833340462,
    "tti": 0.5952799999999999
  },
  {
    "timestamp": "2025-09-30T09:43:44.378Z",
    "performance": 100,
    "fcp": 0.25288000000000005,
    "lcp": 0.593268,
    "tbt": 0,
    "cls": 0,
    "speedIndex": 0.31105299167023104,
    "tti": 0.593268
  },
  {
    "timestamp": "2025-09-30T09:45:20.424Z",
    "performance": 100,
    "fcp": 0.25312300000000004,
    "lcp": 0.595923,
    "tbt": 0,
    "cls": 0,
    "speedIndex": 0.3053189666661183,
    "tti": 0.595923
  },
  {
    "timestamp": "2025-09-30T09:47:19.007Z",
    "performance": 100,
    "fcp": 0.25846299999999994,
    "lcp": 0.25846299999999994,
    "tbt": 0,
    "cls": 0,
    "speedIndex": 0.3834005666918913,
    "tti": 0.25846299999999994
  },
  {
    "timestamp": "2025-09-30T15:52:27.666Z",
    "performance": 100,
    "fcp": 0.253413,
    "lcp": 0.253413,
    "tbt": 0,
    "cls": 0,
    "speedIndex": 0.31281062500987056,
    "tti": 0.25341300000000005
  },
  {
    "timestamp": "2025-09-30T15:53:54.510Z",
    "performance": 100,
    "fcp": 0.24815099999999995,
    "lcp": 0.59114,
    "tbt": 0,
    "cls": 0,
    "speedIndex": 0.38425472500987046,
    "tti": 0.59114
  },
  {
    "timestamp": "2025-09-30T15:55:00.869Z",
    "performance": 100,
    "fcp": 0.256107,
    "lcp": 0.623108,
    "tbt": 0,
    "cls": 0,
    "speedIndex": 0.40420375002851483,
    "tti": 0.623108
  },
  {
    "timestamp": "2025-09-30T15:55:46.849Z",
    "performance": 100,
    "fcp": 0.254286,
    "lcp": 0.589563,
    "tbt": 0,
    "cls": 0,
    "speedIndex": 0.32773675001699926,
    "tti": 0.5895630000000001
  },
  {
    "timestamp": "2025-09-30T15:56:09.426Z",
    "performance": 100,
    "fcp": 0.25442000000000004,
    "lcp": 0.597248,
    "tbt": 0,
    "cls": 0,
    "speedIndex": 0.3180420083366235,
    "tti": 0.597248
  },
  {
    "timestamp": "2025-09-30T15:56:55.679Z",
    "performance": 100,
    "fcp": 0.25507500000000005,
    "lcp": 0.5955240000000002,
    "tbt": 0,
    "cls": 0,
    "speedIndex": 0.3265520500087738,
    "tti": 0.5955240000000002
  },
  {
    "timestamp": "2025-09-30T15:59:49.301Z",
    "performance": 100,
    "fcp": 0.255334,
    "lcp": 0.5837960000000001,
    "tbt": 0,
    "cls": 0,
    "speedIndex": 0.3340882666699568,
    "tti": 0.5837960000000001
  },
  {
    "timestamp": "2025-09-30T16:59:59.704Z",
    "performance": 100,
    "fcp": 0.25772000000000006,
    "lcp": 0.5945199999999999,
    "tbt": 0,
    "cls": 0,
    "speedIndex": 0.4331281083075603,
    "tti": 0.5945199999999999
  }
]